urn.py
urn-0.1.3.dist-info/LICENSE
urn-0.1.3.dist-info/WHEEL
urn-0.1.3.dist-info/METADATA
urn-0.1.3.dist-info/RECORD
